config/__init__.py
config/api_router.py
config/celery_app.py
config/urls.py
config/wsgi.py
config/settings/__init__.py
config/settings/base.py
config/settings/local.py
config/settings/production.py
config/settings/test.py
demo_cookiecutter/__init__.py
demo_cookiecutter/conftest.py
demo_cookiecutter/contrib/__init__.py
demo_cookiecutter/contrib/sites/__init__.py
demo_cookiecutter/contrib/sites/migrations/0001_initial.py
demo_cookiecutter/contrib/sites/migrations/0002_alter_domain_unique.py
demo_cookiecutter/contrib/sites/migrations/0003_set_site_domain_and_name.py
demo_cookiecutter/contrib/sites/migrations/0004_alter_options_ordering_domain.py
demo_cookiecutter/contrib/sites/migrations/__init__.py
demo_cookiecutter/users/__init__.py
demo_cookiecutter/users/adapters.py
demo_cookiecutter/users/admin.py
demo_cookiecutter/users/apps.py
demo_cookiecutter/users/context_processors.py
demo_cookiecutter/users/forms.py
demo_cookiecutter/users/models.py
demo_cookiecutter/users/tasks.py
demo_cookiecutter/users/urls.py
demo_cookiecutter/users/views.py
demo_cookiecutter/users/migrations/0001_initial.py
demo_cookiecutter/users/migrations/__init__.py
demo_cookiecutter/users/tests/__init__.py
demo_cookiecutter/users/tests/factories.py
demo_cookiecutter/users/tests/test_admin.py
demo_cookiecutter/users/tests/test_drf_urls.py
demo_cookiecutter/users/tests/test_drf_views.py
demo_cookiecutter/users/tests/test_forms.py
demo_cookiecutter/users/tests/test_models.py
demo_cookiecutter/users/tests/test_swagger.py
demo_cookiecutter/users/tests/test_tasks.py
demo_cookiecutter/users/tests/test_urls.py
demo_cookiecutter/users/tests/test_views.py
demo_cookiecutter/utils/__init__.py
demo_cookiecutter/utils/storages.py
polls/__init__.py
polls/admin.py
polls/apps.py
polls/models.py
polls/tests.py
polls/urls.py
polls/views.py
polls/migrations/0001_initial.py
polls/migrations/__init__.py
polls/static/polls/style.css
polls/static/polls/images/background.jpg
polls/templates/polls/detail.html
django_cookie_cutter_polls-0.2.dist-info/LICENSE
django_cookie_cutter_polls-0.2.dist-info/METADATA
django_cookie_cutter_polls-0.2.dist-info/WHEEL
django_cookie_cutter_polls-0.2.dist-info/top_level.txt
django_cookie_cutter_polls-0.2.dist-info/RECORD
