Metadata-Version: 2.1
Name: django-cookie-cutter-polls
Version: 0.2
Summary: A Django app to conduct web-based polls.
Home-page: https://www.example.com/
Author: Your Name
Author-email: yourname@example.com
License: BSD-3-Clause  # Example license
Classifier: Environment :: Web Environment
Classifier: Intended Audience :: Developers
Classifier: License :: OSI Approved :: BSD License
Classifier: Operating System :: OS Independent
Classifier: Programming Language :: Python
Classifier: Programming Language :: Python :: 3
Classifier: Programming Language :: Python :: 3 :: Only
Classifier: Programming Language :: Python :: 3.8
Classifier: Programming Language :: Python :: 3.9
Classifier: Topic :: Internet :: WWW/HTTP
Classifier: Topic :: Internet :: WWW/HTTP :: Dynamic Content
Requires-Python: >=3.11
License-File: LICENSE
Requires-Dist: Django >=4.2
